api_chatbots/__init__.py
api_chatbots/myfunctions.py
api_chatbots-0.1.6.dist-info/METADATA
api_chatbots-0.1.6.dist-info/WHEEL
api_chatbots-0.1.6.dist-info/RECORD
