Metadata-Version: 2.3
Name: api_chatbots
Version: 0.1.6
Summary: Facilitates interaction with API LLMs such as ChatGPT, Claude, and Gemini
Author-email: Nicolas Gatien <nicolas.gatien6@gmail.com>
Requires-Python: >=3.8
Requires-Dist: openai==1.55.0
